{"data": {"productCategory": {"id": "148", "name": "Invoicing tools", "description": "These tools provide efficient and streamlined solutions for generating professional invoices, tracking payments, and managing billing processes.", "expandableHtml": null, "slug": "invoicing-tools", "path": "/categories/invoicing-tools", "orbitAwardInfo": null, "meta": {"title": "The best invoicing tools in 2026", "__typename": "MetaTags"}, "targetedAd": {"id": "32987", "subject": "Channel", "post": {"id": "437142", "slug": "ai-figma-to-code-by-anima", "name": "AI Figma to Code by Anima", "updatedAt": "2026-01-17T08:55:53-08:00", "commentsCount": 12, "topics": {"edges": [{"node": {"id": "44", "slug": "design-tools", "name": "Design Tools", "__typename": "Topic"}, "__typename": "TopicEdge"}, {"node": {"id": "267", "slug": "developer-tools", "name": "Developer Tools", "__typename": "Topic"}, "__typename": "TopicEdge"}, {"node": {"id": "268", "slug": "artificial-intelligence", "name": "Artificial Intelligence", "__typename": "Topic"}, "__typename": "TopicEdge"}], "__typename": "TopicConnection"}, "featuredComment": null, "hasVoted": false, "latestScore": 177, "launchDayScore": 138, "disabledWhenScheduled": true, "featuredAt": "2024-01-30T00:01:00-08:00", "createdAt": "2024-01-30T00:01:00-08:00", "embargoPreviewAt": null, "product": {"id": "111800", "isSubscribed": false, "__typename": "Product", "slug": "anima-app"}, "__typename": "Post", "hideVotesCount": false}, "name": "Anima - OnBrand Vibe Coding", "tagline": "Design-aware AI for modern product teams.", "thumbnailUuid": "a91e6d85-b06b-4f82-a9e7-8d06199e0a10.gif", "largeAssetUuid": null, "smallAssetUuid": null, "url": "/r/ad/32987", "variationId": null, "__typename": "Ad"}, "heroProducts": {"edges": [{"node": {"id": "112063", "name": "Stripe", "logoUuid": "7a01a00b-d41d-4367-b44e-e1d0a672819b.jpeg", "isNoLongerOnline": false, "__typename": "Product"}, "__typename": "ProductEdge"}, {"node": {"id": "563102", "name": "Usequeue", "logoUuid": "ad5ebf69-433d-4c60-878f-2c87b0a93fba.png", "isNoLongerOnline": false, "__typename": "Product"}, "__typename": "ProductEdge"}, {"node": {"id": "514757", "name": "WorkZone", "logoUuid": "d77ccbde-8c35-47ed-a90c-d54090638d54.png", "isNoLongerOnline": false, "__typename": "Product"}, "__typename": "ProductEdge"}, {"node": {"id": "550116", "name": "Streamlined", "logoUuid": "53644e31-de48-453e-a29c-ca16969f7ff9.png", "isNoLongerOnline": false, "__typename": "Product"}, "__typename": "ProductEdge"}, {"node": {"id": "582020", "name": "FISKL", "logoUuid": "2e823112-2a29-4e14-b197-dfeaf215e93a.jpeg", "isNoLongerOnline": false, "__typename": "Product"}, "__typename": "ProductEdge"}, {"node": {"id": "564768", "name": "Rainex", "logoUuid": "83291b6d-5c4c-4814-a9fa-07acc1da9cc6.png", "isNoLongerOnline": false, "__typename": "Product"}, "__typename": "ProductEdge"}], "totalCount": 160, "__typename": "ProductsConnection"}, "parent": {"id": "141", "name": "Finance", "path": "/categories/finance", "__typename": "ProductCategory", "subCategories": {"edges": [{"node": {"id": "143", "name": "Accounting software", "path": "/categories/accounting", "__typename": "ProductCategory"}, "__typename": "ProductCategoryEdge"}, {"node": {"id": "144", "name": "Budgeting apps", "path": "/categories/budgeting-and-expense-tracking", "__typename": "ProductCategory"}, "__typename": "ProductCategoryEdge"}, {"node": {"id": "159", "name": "Credit score tools", "path": "/categories/credit-scores", "__typename": "ProductCategory"}, "__typename": "ProductCategoryEdge"}, {"node": {"id": "154", "name": "Financial planning", "path": "/categories/financial-planning", "__typename": "ProductCategory"}, "__typename": "ProductCategoryEdge"}, {"node": {"id": "529", "name": "Fundraising resources", "path": "/categories/fundraising-resources", "__typename": "ProductCategory"}, "__typename": "ProductCategoryEdge"}, {"node": {"id": "335", "name": "Investing", "path": "/categories/investing", "__typename": "ProductCategory"}, "__typename": "ProductCategoryEdge"}, {"node": {"id": "148", "name": "Invoicing tools", "path": "/categories/invoicing-tools", "__typename": "ProductCategory"}, "__typename": "ProductCategoryEdge"}, {"node": {"id": "162", "name": "Money transfer", "path": "/categories/money-transfer", "__typename": "ProductCategory"}, "__typename": "ProductCategoryEdge"}, {"node": {"id": "156", "name": "Neobanks", "path": "/categories/neobanks", "__typename": "ProductCategory"}, "__typename": "ProductCategoryEdge"}, {"node": {"id": "152", "name": "Online banking", "path": "/categories/online-banking", "__typename": "ProductCategory"}, "__typename": "ProductCategoryEdge"}, {"node": {"id": "149", "name": "Payroll software", "path": "/categories/payroll", "__typename": "ProductCategory"}, "__typename": "ProductCategoryEdge"}, {"node": {"id": "150", "name": "Remote workforce tools", "path": "/categories/remote-workforce", "__typename": "ProductCategory"}, "__typename": "ProductCategoryEdge"}, {"node": {"id": "146", "name": "Retirement planning", "path": "/categories/retirement-planning", "__typename": "ProductCategory"}, "__typename": "ProductCategoryEdge"}, {"node": {"id": "147", "name": "Savings apps", "path": "/categories/savings-apps", "__typename": "ProductCategory"}, "__typename": "ProductCategoryEdge"}, {"node": {"id": "155", "name": "Startup financial planning", "path": "/categories/startup-financial-planning", "__typename": "ProductCategory"}, "__typename": "ProductCategoryEdge"}, {"node": {"id": "1453", "name": "Startup incorporation", "path": "/categories/startup-incorporation", "__typename": "ProductCategory"}, "__typename": "ProductCategoryEdge"}, {"node": {"id": "161", "name": "Stock trading platforms", "path": "/categories/stock-trading", "__typename": "ProductCategory"}, "__typename": "ProductCategoryEdge"}, {"node": {"id": "145", "name": "Tax preparation", "path": "/categories/tax-preparation", "__typename": "ProductCategory"}, "__typename": "ProductCategoryEdge"}, {"node": {"id": "1321", "name": "Treasury management platforms", "path": "/categories/treasury-management-platforms", "__typename": "ProductCategory"}, "__typename": "ProductCategoryEdge"}], "__typename": "ProductCategoryConnection"}}, "__typename": "ProductCategory", "subCategories": {"edges": [], "__typename": "ProductCategoryConnection"}, "recentSummary": {"summary": "[Invoce.ai](https://www.producthunt.com/products/invoce-ai) speeds freelancer billing with chat-to-invoice, client/item databases, and branded exports while letting users attach their own payment links. [Assembly](https://www.producthunt.com/products/assembly-7) suits service firms needing branded portals that unify messaging, document sharing, invoicing, and AI\u2011assisted CRM. For receivables at scale, [TurboAR](https://www.producthunt.com/products/turboar) automates invoice tracking and follow-ups with collaborative workflows to reduce aging without spreadsheet sprawl.", "products": [{"id": "1144668", "slug": "invoce-ai", "name": "Invoce.ai", "tagline": "Chat with AI to create invoices in seconds", "logoUuid": "a4b8f3a2-c6b5-45ac-b66d-30d39b86ebec.svg", "reviewsRating": 0.0, "reviewsCount": 0, "categories": [{"id": "148", "name": "Invoicing tools", "slug": "invoicing-tools", "path": "/categories/invoicing-tools", "__typename": "ProductCategory"}], "tags": ["instant invoice generation", "chat-based invoice creation", "freelancer and smb focused", "professional invoice templates", "productivity", "saas", "artificial intelligence", "invoicing tools"], "embeddingSummary": null, "isTopProduct": false, "badges": {"edges": [], "__typename": "Connection"}, "followersCount": 168, "isSubscribed": false, "__typename": "Product", "isNoLongerOnline": false, "latestLaunch": {"id": "1057838", "scheduledAt": "2026-01-05T00:01:00-08:00", "__typename": "Post"}}, {"id": "1109444", "slug": "assembly-7", "name": "Assembly", "tagline": "Branded customer portals & AI-powered CRM", "logoUuid": "b4d7f4f5-0119-4ccb-a55d-3093b3494eed.png", "reviewsRating": 5.0, "reviewsCount": 10, "categories": [{"id": "55", "name": "Customer support tools", "slug": "customer-support", "path": "/categories/customer-support", "__typename": "ProductCategory"}, {"id": "96", "name": "CRM software", "slug": "crm", "path": "/categories/crm", "__typename": "ProductCategory"}, {"id": "148", "name": "Invoicing tools", "slug": "invoicing-tools", "path": "/categories/invoicing-tools", "__typename": "ProductCategory"}], "tags": ["customer success", "artificial intelligence", "crm", "customer support", "invoicing tools"], "embeddingSummary": null, "isTopProduct": false, "badges": {"edges": [{"node": {"id": "7147131", "post": {"id": "1018068", "slug": "assembly-9", "name": "Assembly", "product": {"id": "1109444", "slug": "assembly-7", "__typename": "Product"}, "redirectToProduct": {"id": "1109444", "slug": "assembly-7", "__typename": "Product"}, "__typename": "Post"}, "position": 4, "period": "daily", "date": "2025-09-30", "__typename": "TopPostBadge"}, "__typename": "BadgeEdge"}], "__typename": "Connection"}, "followersCount": 957, "isSubscribed": false, "__typename": "Product", "isNoLongerOnline": false, "latestLaunch": {"id": "1018068", "scheduledAt": "2025-09-30T00:01:00-07:00", "__typename": "Post"}}, {"id": "594758", "slug": "turboar", "name": "TurboAR", "tagline": "Automate Invoice Followups, Work Together, Collect Payments.", "logoUuid": "320b5132-502b-422b-bd75-accf0805a20c.jpeg", "reviewsRating": 0.0, "reviewsCount": 0, "categories": [{"id": "37", "name": "Team collaboration software", "slug": "team-collaboration", "path": "/categories/team-collaboration", "__typename": "ProductCategory"}, {"id": "143", "name": "Accounting software", "slug": "accounting", "path": "/categories/accounting", "__typename": "ProductCategory"}, {"id": "148", "name": "Invoicing tools", "slug": "invoicing-tools", "path": "/categories/invoicing-tools", "__typename": "ProductCategory"}], "tags": ["payments", "spreadsheets", "accounting", "invoicing tools"], "embeddingSummary": null, "isTopProduct": false, "badges": {"edges": [], "__typename": "Connection"}, "followersCount": 63, "isSubscribed": false, "__typename": "Product", "isNoLongerOnline": false, "latestLaunch": {"id": "473108", "scheduledAt": "2024-07-26T00:01:00-07:00", "__typename": "Post"}}], "__typename": "ProductsSummary"}, "recentLaunches": {"totalCount": 160, "__typename": "ProductsConnection"}, "questions": [], "discussions": {"edges": [{"node": {"id": "755140", "pageViewsCount": 207, "slug": "what-s-the-easiest-no-code-tool-for-handling-subscriptions-payments", "createdAt": "2025-09-26T03:48:43-07:00", "path": "/p/vibecoding/what-s-the-easiest-no-code-tool-for-handling-subscriptions-payments", "title": "What\u2019s the easiest no-code tool for handling subscriptions + payments?", "descriptionPreview": "Hey Makers I m exploring options for managing subscriptions, payments, and authentication in a super simple way. Ideally, something that s: 1.\tNo-code / low-code friendly 2.\tEasy to integrate without a ton of setup 3.\tHandles the boring stuff like billing, invoicing, cancellations, and user access automatically\nI ve looked at a few tools, but many feel too heavy for a small MVP. Curious to know: What are you using right now? Any lightweight tools that worked really well for your early-stage product? Bonus if it has a generous free tier or is affordable for indie founders. Would love to hear what s working for this community before I commit to something!", "featuredAt": null, "pinned": false, "user": {"id": "3941516", "name": "Mohit Mohta", "username": "mohtamohit", "avatarUrl": "https://ph-avatars.imgix.net/3941516/original.jpeg", "__typename": "User", "isAccountVerified": false, "isAmbassador": false, "selectedBylineProduct": null, "topProductBadge": null, "topHunterBadge": null, "topLaunchBadge": null}, "hasVoted": false, "votesCount": 33, "__typename": "DiscussionThread", "commentsCount": 10, "featuredComment": null, "primaryForum": {"id": "472520", "slug": "vibecoding", "subject": {"id": "201", "name": "Vibecoding", "thumbnailUuid": "379b8fc1-a8e0-48f3-be0c-15e11b165944.svg", "__typename": "DiscussionCategory"}, "__typename": "DiscussionForumType"}}, "__typename": "DiscussionThreadEdge"}, {"node": {"id": "682964", "pageViewsCount": 261, "slug": "what-are-best-payment-gateways-for-global-sales", "createdAt": "2025-03-23T09:03:08-07:00", "path": "/p/general/what-are-best-payment-gateways-for-global-sales", "title": "What are best payment gateways for global sales?", "descriptionPreview": "<p>If you're a SaaS, digital product, agency or freelancer what payment gateways do you use to handle local methods, taxes and subscriptions? </p><p>PayPal charges me 5% per transaction and their support is unwilling to reduce it to 3% for me while I know they do lower the transaction fee for certain accounts. </p>", "featuredAt": null, "pinned": false, "user": {"id": "4325010", "name": "Rohan Chaubey", "username": "rohanrecommends", "avatarUrl": "https://ph-avatars.imgix.net/4325010/a8bdb2a7-d1ec-444a-9823-2833c30c540c.jpeg", "__typename": "User", "isAccountVerified": true, "isAmbassador": false, "selectedBylineProduct": null, "topProductBadge": null, "topHunterBadge": null, "topLaunchBadge": null}, "hasVoted": false, "votesCount": 31, "__typename": "DiscussionThread", "commentsCount": 12, "featuredComment": null, "primaryForum": {"id": "7", "slug": "general", "subject": {"id": "100", "name": "General", "thumbnailUuid": "85c8f053-f68f-486f-a83b-79bd21080edc.svg", "__typename": "DiscussionCategory"}, "__typename": "DiscussionForumType"}}, "__typename": "DiscussionThreadEdge"}, {"node": {"id": "99238", "pageViewsCount": 32, "slug": "question-to-all-founders-and-managers-what-tools-do-you-use-to-manage-your-business-expenses", "createdAt": "2021-06-14T00:00:00-07:00", "path": "/p/general/question-to-all-founders-and-managers-what-tools-do-you-use-to-manage-your-business-expenses", "title": "Question to all founders and managers: What tools do you use to manage your business expenses?", "descriptionPreview": "I'm new to the fintech space and I'd love to know more about some tools/software that help manage business expenses and improve the efficiency of your finance and accounting teams. What tools do you use for: - managing your business expenses - sales, marketing, product expenses, etc\n- paying for software and other subscriptions\n- employee reimbursement and claims\n- accounting automation\n- travel and miscellaneous expenses Eager to know and learn more from you all. Thanks guys :)", "featuredAt": "2021-06-21", "pinned": false, "user": {"id": "3470181", "name": "Pranav Harish", "username": "pranav_harish", "avatarUrl": "https://ph-avatars.imgix.net/3470181/original.jpeg", "__typename": "User", "isAccountVerified": false, "isAmbassador": false, "selectedBylineProduct": {"id": "463131", "name": "Volopay", "slug": "volopay", "logoUuid": "fcf22077-9e5a-4ccd-b34c-b171611b6113.gif", "isNoLongerOnline": false, "__typename": "Product"}, "topProductBadge": null, "topHunterBadge": null, "topLaunchBadge": null}, "hasVoted": false, "votesCount": 38, "__typename": "DiscussionThread", "commentsCount": 12, "featuredComment": null, "primaryForum": {"id": "7", "slug": "general", "subject": {"id": "100", "name": "General", "thumbnailUuid": "85c8f053-f68f-486f-a83b-79bd21080edc.svg", "__typename": "DiscussionCategory"}, "__typename": "DiscussionForumType"}}, "__typename": "DiscussionThreadEdge"}, {"node": {"id": "285055", "pageViewsCount": 6, "slug": "can-anyone-recommend-a-tool-or-software-for-user-tracking", "createdAt": "2024-07-01T00:20:31-07:00", "path": "/p/general/can-anyone-recommend-a-tool-or-software-for-user-tracking", "title": "Can anyone recommend a tool or software for user tracking?", "descriptionPreview": "Any tool or software, that enables tracking users' signups and billing with tracking up insights.", "featuredAt": null, "pinned": false, "user": {"id": "7138659", "name": "Harsh Gupta", "username": "harshxgrowth", "avatarUrl": "https://ph-avatars.imgix.net/7138659/a06c997e-2056-410a-94ad-2292c43f91b0.png", "__typename": "User", "isAccountVerified": false, "isAmbassador": false, "selectedBylineProduct": null, "topProductBadge": null, "topHunterBadge": null, "topLaunchBadge": null}, "hasVoted": false, "votesCount": 7, "__typename": "DiscussionThread", "commentsCount": 13, "featuredComment": null, "primaryForum": {"id": "7", "slug": "general", "subject": {"id": "100", "name": "General", "thumbnailUuid": "85c8f053-f68f-486f-a83b-79bd21080edc.svg", "__typename": "DiscussionCategory"}, "__typename": "DiscussionForumType"}}, "__typename": "DiscussionThreadEdge"}], "pageInfo": {"hasNextPage": true, "__typename": "PageInfo"}, "__typename": "DiscussionThreadConnection"}, "relevantReviews": {"edges": [], "__typename": "ProductCategoryRelevantReviewConnection"}}}}