{"data": {"productCategory": {"id": "66", "path": "/categories/3d-animation", "slug": "3d-animation", "description": "Explore tools for creating and animating 3D scenes, motion graphics, and VR. Build models, rig, render, and design interactive visuals for apps, games, and web.", "name": "3D & Animation", "aiSummary": {"summary": "[Mathify](https://www.producthunt.com/products/mathify-4) targets STEM visuals with natural\u2011language Manim generation, GPU cloud renders, and VTK exports for inspectable 3D. [Gamelabs Studio](https://www.producthunt.com/products/gamelabs-studio) accelerates 2D game pipelines via text-to-animation, looped spritesheets, and IDE integration. [Kaedim](https://www.producthunt.com/products/kaedim) streamlines 3D asset creation with 2D\u2011to\u20113D, auto\u2011texturing, and production tracking\u2014suited to studios needing faster prototyping, consistent outputs, and managed review workflows across complex pipelines.", "__typename": "ProductsSummary"}, "categoryTags": [{"name": "design tools", "count": 129, "__typename": "ProductTagWithCount"}, {"name": "3d modeling", "count": 78, "__typename": "ProductTagWithCount"}, {"name": "artificial intelligence", "count": 76, "__typename": "ProductTagWithCount"}, {"name": "tech", "count": 75, "__typename": "ProductTagWithCount"}, {"name": "ai generative media", "count": 55, "__typename": "ProductTagWithCount"}, {"name": "augmented reality", "count": 49, "__typename": "ProductTagWithCount"}, {"name": "developer tools", "count": 49, "__typename": "ProductTagWithCount"}, {"name": "productivity", "count": 47, "__typename": "ProductTagWithCount"}, {"name": "graphic design tools", "count": 47, "__typename": "ProductTagWithCount"}, {"name": "web app", "count": 43, "__typename": "ProductTagWithCount"}, {"name": "marketing", "count": 42, "__typename": "ProductTagWithCount"}, {"name": "animation", "count": 37, "__typename": "ProductTagWithCount"}, {"name": "design resources", "count": 35, "__typename": "ProductTagWithCount"}, {"name": "video editing", "count": 32, "__typename": "ProductTagWithCount"}, {"name": "games", "count": 31, "__typename": "ProductTagWithCount"}, {"name": "animation tools", "count": 30, "__typename": "ProductTagWithCount"}, {"name": "template library", "count": 25, "__typename": "ProductTagWithCount"}, {"name": "user experience", "count": 22, "__typename": "ProductTagWithCount"}, {"name": "video", "count": 21, "__typename": "ProductTagWithCount"}, {"name": "ai-generated visuals", "count": 20, "__typename": "ProductTagWithCount"}], "products": {"edges": [{"node": {"id": "536566", "detailedReviewsCount": 37, "postsCount": 3, "latestLaunch": {"id": "460991", "scheduledAt": "2024-06-06T00:01:00-07:00", "__typename": "Post"}, "slug": "recraft-ai", "name": "Recraft", "tagline": "Image generation for professionals", "logoUuid": "39d1d4eb-e5e5-4125-8f98-24b9cfa940b6.png", "reviewsRating": 4.81, "reviewsCount": 37, "categories": [{"id": "66", "name": "3D & Animation", "slug": "3d-animation", "path": "/categories/3d-animation", "__typename": "ProductCategory"}, {"id": "125", "name": "AI Generative Media", "slug": "ai-generative-media", "path": "/categories/ai-generative-media", "__typename": "ProductCategory"}, {"id": "234", "name": "Graphic design tools", "slug": "graphic-design-tools", "path": "/categories/graphic-design-tools", "__typename": "ProductCategory"}], "tags": ["vector editing", "free for commercial use", "ai-generated visuals", "3d modeling", "style-consistent design", "design tools", "marketing", "artificial intelligence", "graphic design", "3d & animation", "ai generative media", "graphic design tools"], "embeddingSummary": null, "isTopProduct": false, "badges": {"edges": [{"node": {"id": "2847341", "post": {"id": "396873", "slug": "recraft-ai", "name": "Recraft.AI", "product": {"id": "536566", "slug": "recraft-ai", "__typename": "Product"}, "redirectToProduct": {"id": "536566", "slug": "recraft-ai", "__typename": "Product"}, "__typename": "Post"}, "position": 5, "period": "weekly", "date": "2023-05-31", "__typename": "TopPostBadge"}, "__typename": "BadgeEdge"}, {"node": {"id": "2827188", "post": {"id": "396873", "slug": "recraft-ai", "name": "Recraft.AI", "product": {"id": "536566", "slug": "recraft-ai", "__typename": "Product"}, "redirectToProduct": {"id": "536566", "slug": "recraft-ai", "__typename": "Product"}, "__typename": "Post"}, "position": 2, "period": "daily", "date": "2023-05-31", "__typename": "TopPostBadge"}, "__typename": "BadgeEdge"}], "__typename": "Connection"}, "followersCount": 1948, "isSubscribed": false, "__typename": "Product", "isNoLongerOnline": false, "founderReviewsCount": 13, "founderShoutouts": [{"id": "310431", "product": {"id": "536566", "__typename": "Product"}, "fromPost": {"id": "941668", "slug": "second-me-by-me-bot", "name": "Second.Me by Me.bot", "product": {"id": "540236", "slug": "mindos", "__typename": "Product"}, "badges": {"edges": [{"node": {"__typename": "TopPostBadge", "id": "5536405", "position": 2, "period": "daily", "date": "2025-03-21"}, "__typename": "BadgeEdge"}], "__typename": "Connection"}, "__typename": "Post", "thumbnailImageUuid": "c9248ace-5563-44f9-ac60-529e7410715f.jpeg", "productState": "default"}, "__typename": "DetailedReview"}, {"id": "350253", "product": {"id": "536566", "__typename": "Product"}, "fromPost": {"id": "1007536", "slug": "sprout-track", "name": "Sprout Track", "product": {"id": "1100144", "slug": "sprout-track-the-beta-launch", "__typename": "Product"}, "badges": {"edges": [], "__typename": "Connection"}, "__typename": "Post", "thumbnailImageUuid": "1a0d94f7-dcee-47c3-bcb8-fd625fb24b79.png", "productState": "default"}, "__typename": "DetailedReview"}]}, "__typename": "ProductEdge"}, {"node": {"id": "568007", "detailedReviewsCount": 0, "postsCount": 1, "latestLaunch": {"id": "435334", "scheduledAt": "2024-01-19T00:01:00-08:00", "__typename": "Post"}, "slug": "neverscene", "name": "Neverscene", "tagline": "Create Unique Interiors Inspired by Your Moodboard", "logoUuid": "77edf1f7-6ee2-429e-8efd-46f438290b9b.png", "reviewsRating": 0.0, "reviewsCount": 0, "categories": [{"id": "66", "name": "3D & Animation", "slug": "3d-animation", "path": "/categories/3d-animation", "__typename": "ProductCategory"}, {"id": "125", "name": "AI Generative Media", "slug": "ai-generative-media", "path": "/categories/ai-generative-media", "__typename": "ProductCategory"}], "tags": ["home", "artificial intelligence", "interior design", "3d & animation", "ai generative media"], "embeddingSummary": null, "isTopProduct": false, "badges": {"edges": [], "__typename": "Connection"}, "followersCount": 87, "isSubscribed": false, "__typename": "Product", "isNoLongerOnline": false, "founderReviewsCount": 0, "founderShoutouts": []}, "__typename": "ProductEdge"}, {"node": {"id": "567601", "detailedReviewsCount": 1, "postsCount": 1, "latestLaunch": {"id": "434713", "scheduledAt": "2024-01-16T00:01:00-08:00", "__typename": "Post"}, "slug": "nomad-sculpt", "name": "Nomad Sculpt", "tagline": "A sculpting and painting mobile application", "logoUuid": "54902386-08e5-479d-8e5e-bd40404834af.webp", "reviewsRating": 5.0, "reviewsCount": 1, "categories": [{"id": "63", "name": "Mobile editing apps", "slug": "mobile-editing", "path": "/categories/mobile-editing", "__typename": "ProductCategory"}, {"id": "66", "name": "3D & Animation", "slug": "3d-animation", "path": "/categories/3d-animation", "__typename": "ProductCategory"}], "tags": ["android", "design tools", "art", "3d modeling", "mobile editing", "3d & animation"], "embeddingSummary": null, "isTopProduct": false, "badges": {"edges": [], "__typename": "Connection"}, "followersCount": 98, "isSubscribed": false, "__typename": "Product", "isNoLongerOnline": false, "founderReviewsCount": 1, "founderShoutouts": [{"id": "325193", "product": {"id": "567601", "__typename": "Product"}, "fromPost": {"id": "964449", "slug": "xogot", "name": "Xogot", "product": {"id": "1064477", "slug": "xogot-make-games-anywhere", "__typename": "Product"}, "badges": {"edges": [], "__typename": "Connection"}, "__typename": "Post", "thumbnailImageUuid": "ecb1e879-6049-4a67-98ce-7dd6cf1c50b5.png", "productState": "default"}, "__typename": "DetailedReview"}]}, "__typename": "ProductEdge"}, {"node": {"id": "567242", "detailedReviewsCount": 1, "postsCount": 1, "latestLaunch": {"id": "434238", "scheduledAt": "2024-01-15T00:08:45-08:00", "__typename": "Post"}, "slug": "realitymax", "name": "RealityMAX", "tagline": "Real-time 3D collaboration meets no-code augmented reality", "logoUuid": "9c9e80f2-fd99-484a-bf20-30f478b3249d.png", "reviewsRating": 5.0, "reviewsCount": 1, "categories": [{"id": "37", "name": "Team collaboration software", "slug": "team-collaboration", "path": "/categories/team-collaboration", "__typename": "ProductCategory"}, {"id": "44", "name": "Presentation Software", "slug": "presentation-software", "path": "/categories/presentation-software", "__typename": "ProductCategory"}, {"id": "66", "name": "3D & Animation", "slug": "3d-animation", "path": "/categories/3d-animation", "__typename": "ProductCategory"}], "tags": ["design tools", "productivity", "augmented reality", "presentation software", "3d & animation"], "embeddingSummary": null, "isTopProduct": false, "badges": {"edges": [], "__typename": "Connection"}, "followersCount": 148, "isSubscribed": false, "__typename": "Product", "isNoLongerOnline": false, "founderReviewsCount": 0, "founderShoutouts": []}, "__typename": "ProductEdge"}, {"node": {"id": "566669", "detailedReviewsCount": 0, "postsCount": 1, "latestLaunch": {"id": "433521", "scheduledAt": "2024-01-09T01:01:57-08:00", "__typename": "Post"}, "slug": "items-design", "name": "Items Design", "tagline": "Free AI Generated Design Assets", "logoUuid": "5d30db9f-f1f5-4fce-909b-0b96778ffc7e.png", "reviewsRating": 0.0, "reviewsCount": 0, "categories": [{"id": "66", "name": "3D & Animation", "slug": "3d-animation", "path": "/categories/3d-animation", "__typename": "ProductCategory"}, {"id": "125", "name": "AI Generative Media", "slug": "ai-generative-media", "path": "/categories/ai-generative-media", "__typename": "ProductCategory"}, {"id": "235", "name": "Design resources", "slug": "design-resources", "path": "/categories/design-resources", "__typename": "ProductCategory"}], "tags": ["template library", "free for commercial use", "illustration library", "ai-generated visuals", "svg export", "marketing", "artificial intelligence", "design", "3d & animation", "ai generative media", "design resources"], "embeddingSummary": null, "isTopProduct": false, "badges": {"edges": [{"node": {"id": "3639260", "post": {"id": "433521", "slug": "items-design", "name": "Items Design", "product": {"id": "566669", "slug": "items-design", "__typename": "Product"}, "redirectToProduct": {"id": "566669", "slug": "items-design", "__typename": "Product"}, "__typename": "Post"}, "position": 5, "period": "daily", "date": "2024-01-09", "__typename": "TopPostBadge"}, "__typename": "BadgeEdge"}], "__typename": "Connection"}, "followersCount": 481, "isSubscribed": false, "__typename": "Product", "isNoLongerOnline": false, "founderReviewsCount": 0, "founderShoutouts": []}, "__typename": "ProductEdge"}, {"node": {"id": "566189", "detailedReviewsCount": 1, "postsCount": 1, "latestLaunch": {"id": "432895", "scheduledAt": "2024-01-05T01:06:41-08:00", "__typename": "Post"}, "slug": "pathfinding-on-a-real-map", "name": "Pathfinding on a real map", "tagline": "Pathfinding visualizer on a real map. Anywhere in the world.", "logoUuid": "df6c88a2-a0ef-4316-93f8-fc7ec1f9fe0e.png", "reviewsRating": 5.0, "reviewsCount": 1, "categories": [{"id": "66", "name": "3D & Animation", "slug": "3d-animation", "path": "/categories/3d-animation", "__typename": "ProductCategory"}, {"id": "84", "name": "Data visualization tools", "slug": "data-visualization", "path": "/categories/data-visualization", "__typename": "ProductCategory"}, {"id": "176", "name": "Maps and GPS", "slug": "maps-and-gps", "path": "/categories/maps-and-gps", "__typename": "ProductCategory"}], "tags": ["github", "maps", "tech", "data visualization", "3d & animation", "maps and gps"], "embeddingSummary": null, "isTopProduct": false, "badges": {"edges": [], "__typename": "Connection"}, "followersCount": 71, "isSubscribed": false, "__typename": "Product", "isNoLongerOnline": false, "founderReviewsCount": 0, "founderShoutouts": []}, "__typename": "ProductEdge"}, {"node": {"id": "565273", "detailedReviewsCount": 3, "postsCount": 1, "latestLaunch": {"id": "431591", "scheduledAt": "2024-01-02T00:28:57-08:00", "__typename": "Post"}, "slug": "lottiebox", "name": "Lottiebox", "tagline": "Get-rid from boring and slow web experience", "logoUuid": "519a69ec-6a98-460a-aec2-d916cc649c7f.png", "reviewsRating": 5.0, "reviewsCount": 3, "categories": [{"id": "66", "name": "3D & Animation", "slug": "3d-animation", "path": "/categories/3d-animation", "__typename": "ProductCategory"}, {"id": "234", "name": "Graphic design tools", "slug": "graphic-design-tools", "path": "/categories/graphic-design-tools", "__typename": "ProductCategory"}, {"id": "235", "name": "Design resources", "slug": "design-resources", "path": "/categories/design-resources", "__typename": "ProductCategory"}], "tags": ["template library", "figma integration", "customizable components", "web app", "illustration library", "design tools", "user experience", "animation", "3d & animation", "graphic design tools", "design resources"], "embeddingSummary": null, "isTopProduct": false, "badges": {"edges": [{"node": {"id": "3619550", "post": {"id": "431591", "slug": "lottiebox", "name": "Lottiebox", "product": {"id": "565273", "slug": "lottiebox", "__typename": "Product"}, "redirectToProduct": {"id": "565273", "slug": "lottiebox", "__typename": "Product"}, "__typename": "Post"}, "position": 1, "period": "daily", "date": "2024-01-02", "__typename": "TopPostBadge"}, "__typename": "BadgeEdge"}], "__typename": "Connection"}, "followersCount": 599, "isSubscribed": false, "__typename": "Product", "isNoLongerOnline": false, "founderReviewsCount": 0, "founderShoutouts": []}, "__typename": "ProductEdge"}, {"node": {"id": "564968", "detailedReviewsCount": 3, "postsCount": 1, "latestLaunch": {"id": "431174", "scheduledAt": "2023-12-23T05:19:21-08:00", "__typename": "Post"}, "slug": "creaizi-ar-christmas-card", "name": "Creaizi AR Christmas Card", "tagline": "Unbelievable AR Christmas cards that will wow your friends!", "logoUuid": "818d441b-62f4-45e5-ba56-384bb6fa8f02.png", "reviewsRating": 5.0, "reviewsCount": 3, "categories": [{"id": "66", "name": "3D & Animation", "slug": "3d-animation", "path": "/categories/3d-animation", "__typename": "ProductCategory"}, {"id": "98", "name": "Lead generation software", "slug": "lead-generation", "path": "/categories/lead-generation", "__typename": "ProductCategory"}, {"id": "106", "name": "Messaging apps", "slug": "messaging-apps", "path": "/categories/messaging-apps", "__typename": "ProductCategory"}], "tags": ["customer communication", "augmented reality", "digital art", "3d & animation", "lead generation", "messaging apps"], "embeddingSummary": null, "isTopProduct": false, "badges": {"edges": [], "__typename": "Connection"}, "followersCount": 81, "isSubscribed": false, "__typename": "Product", "isNoLongerOnline": false, "founderReviewsCount": 0, "founderShoutouts": []}, "__typename": "ProductEdge"}, {"node": {"id": "110738", "detailedReviewsCount": 3, "postsCount": 12, "latestLaunch": {"id": "428762", "scheduledAt": "2023-12-07T00:49:07-08:00", "__typename": "Post"}, "slug": "animaker", "name": "Animaker", "tagline": "Animaker, Make Animated Videos on Cloud for free", "logoUuid": "400c1196-6378-443b-b7c1-fef74dc37777.gif", "reviewsRating": 5.0, "reviewsCount": 3, "categories": [{"id": "56", "name": "Design & Creative", "slug": "design-creative", "path": "/categories/design-creative", "__typename": "ProductCategory"}, {"id": "57", "name": "Video editing", "slug": "video-editing", "path": "/categories/video-editing", "__typename": "ProductCategory"}, {"id": "66", "name": "3D & Animation", "slug": "3d-animation", "path": "/categories/3d-animation", "__typename": "ProductCategory"}], "tags": ["template library", "video editing", "ai avatars", "animation tools", "auto-captioning", "ios", "web app", "design tools", "productivity", "home", "social media", "gifs", "marketing", "education", "growth hacking", "artificial intelligence", "tech", "video", "3d & animation"], "embeddingSummary": null, "isTopProduct": false, "badges": {"edges": [{"node": {"id": "3765", "post": {"id": "39888", "slug": "animaker-2", "name": "Animaker", "product": {"id": "110738", "slug": "animaker", "__typename": "Product"}, "redirectToProduct": {"id": "110738", "slug": "animaker", "__typename": "Product"}, "__typename": "Post"}, "position": 3, "period": "daily", "date": "2015-11-07", "__typename": "TopPostBadge"}, "__typename": "BadgeEdge"}], "__typename": "Connection"}, "followersCount": 622, "isSubscribed": false, "__typename": "Product", "isNoLongerOnline": false, "founderReviewsCount": 3, "founderShoutouts": []}, "__typename": "ProductEdge"}, {"node": {"id": "562132", "detailedReviewsCount": 8, "postsCount": 1, "latestLaunch": {"id": "427417", "scheduledAt": "2023-12-05T00:01:00-08:00", "__typename": "Post"}, "slug": "magnific-ai", "name": "Magnific AI", "tagline": "Advanced AI tech to achieve insanely high-res upscaling.", "logoUuid": "0192cede-2a3b-47d4-ae61-69bd98a54800.png", "reviewsRating": 5.0, "reviewsCount": 8, "categories": [{"id": "58", "name": "Photo editing", "slug": "photo-editing", "path": "/categories/photo-editing", "__typename": "ProductCategory"}, {"id": "66", "name": "3D & Animation", "slug": "3d-animation", "path": "/categories/3d-animation", "__typename": "ProductCategory"}, {"id": "125", "name": "AI Generative Media", "slug": "ai-generative-media", "path": "/categories/ai-generative-media", "__typename": "ProductCategory"}], "tags": ["text-to-image", "ai-generated visuals", "high-res upscaling", "ai enhancement", "customizable detail", "artificial intelligence", "photo editing", "3d & animation", "ai generative media"], "embeddingSummary": null, "isTopProduct": false, "badges": {"edges": [], "__typename": "Connection"}, "followersCount": 705, "isSubscribed": false, "__typename": "Product", "isNoLongerOnline": false, "founderReviewsCount": 2, "founderShoutouts": [{"id": "350720", "product": {"id": "562132", "__typename": "Product"}, "fromPost": {"id": "1008480", "slug": "madespace", "name": "Madespace", "product": {"id": "1100956", "slug": "madespace", "__typename": "Product"}, "badges": {"edges": [{"node": {"__typename": "TopPostBadge", "id": "6830744", "position": 4, "period": "daily", "date": "2025-08-23"}, "__typename": "BadgeEdge"}], "__typename": "Connection"}, "__typename": "Post", "thumbnailImageUuid": "684a8e1d-f170-4476-951a-76ad81c4a9b2.png", "productState": "default"}, "__typename": "DetailedReview"}]}, "__typename": "ProductEdge"}, {"node": {"id": "562345", "detailedReviewsCount": 0, "postsCount": 1, "latestLaunch": {"id": "427670", "scheduledAt": "2023-11-30T06:52:49-08:00", "__typename": "Post"}, "slug": "cgdream-ai", "name": "CGDream.ai", "tagline": "Combine 3D and AI to create stunning 2D images.", "logoUuid": "244aea85-4e5d-4a98-a9f9-4064d9e3f330.png", "reviewsRating": 0.0, "reviewsCount": 0, "categories": [{"id": "66", "name": "3D & Animation", "slug": "3d-animation", "path": "/categories/3d-animation", "__typename": "ProductCategory"}, {"id": "125", "name": "AI Generative Media", "slug": "ai-generative-media", "path": "/categories/ai-generative-media", "__typename": "ProductCategory"}], "tags": ["design tools", "artificial intelligence", "digital art", "3d & animation", "ai generative media"], "embeddingSummary": null, "isTopProduct": false, "badges": {"edges": [], "__typename": "Connection"}, "followersCount": 50, "isSubscribed": false, "__typename": "Product", "isNoLongerOnline": false, "founderReviewsCount": 0, "founderShoutouts": []}, "__typename": "ProductEdge"}, {"node": {"id": "562223", "detailedReviewsCount": 0, "postsCount": 1, "latestLaunch": {"id": "427519", "scheduledAt": "2023-11-29T06:47:27-08:00", "__typename": "Post"}, "slug": "nex", "name": "NEX", "tagline": "Multimodal Idea-to-Image Platform for Controlled Generation", "logoUuid": "0e4123aa-8b00-45fd-9095-c9d71841e89f.png", "reviewsRating": 0.0, "reviewsCount": 0, "categories": [{"id": "58", "name": "Photo editing", "slug": "photo-editing", "path": "/categories/photo-editing", "__typename": "ProductCategory"}, {"id": "66", "name": "3D & Animation", "slug": "3d-animation", "path": "/categories/3d-animation", "__typename": "ProductCategory"}, {"id": "234", "name": "Graphic design tools", "slug": "graphic-design-tools", "path": "/categories/graphic-design-tools", "__typename": "ProductCategory"}], "tags": ["design tools", "art", "artificial intelligence", "photo editing", "3d & animation", "graphic design tools"], "embeddingSummary": null, "isTopProduct": false, "badges": {"edges": [], "__typename": "Connection"}, "followersCount": 72, "isSubscribed": false, "__typename": "Product", "isNoLongerOnline": false, "founderReviewsCount": 0, "founderShoutouts": []}, "__typename": "ProductEdge"}, {"node": {"id": "562012", "detailedReviewsCount": 0, "postsCount": 1, "latestLaunch": {"id": "427269", "scheduledAt": "2023-11-28T00:05:55-08:00", "__typename": "Post"}, "slug": "099-supply", "name": "099 Supply", "tagline": "Minimal product mockups", "logoUuid": "adbd1627-b6e5-486a-8470-c3fd78c2e795.png", "reviewsRating": 0.0, "reviewsCount": 0, "categories": [{"id": "66", "name": "3D & Animation", "slug": "3d-animation", "path": "/categories/3d-animation", "__typename": "ProductCategory"}, {"id": "234", "name": "Graphic design tools", "slug": "graphic-design-tools", "path": "/categories/graphic-design-tools", "__typename": "ProductCategory"}, {"id": "236", "name": "Design mockups", "slug": "design-mockups", "path": "/categories/design-mockups", "__typename": "ProductCategory"}], "tags": ["design tools", "photoshop", "graphic design", "3d & animation", "graphic design tools", "design mockups"], "embeddingSummary": null, "isTopProduct": false, "badges": {"edges": [], "__typename": "Connection"}, "followersCount": 132, "isSubscribed": false, "__typename": "Product", "isNoLongerOnline": false, "founderReviewsCount": 0, "founderShoutouts": []}, "__typename": "ProductEdge"}, {"node": {"id": "560228", "detailedReviewsCount": 0, "postsCount": 1, "latestLaunch": {"id": "425108", "scheduledAt": "2023-11-14T02:08:00-08:00", "__typename": "Post"}, "slug": "maps-dioramas-ar", "name": "Maps & Dioramas AR", "tagline": "Make your living room the museum you always wanted to go to.", "logoUuid": "55fb9480-a7c5-4e9f-8bd0-7a7d645124aa.png", "reviewsRating": 0.0, "reviewsCount": 0, "categories": [{"id": "66", "name": "3D & Animation", "slug": "3d-animation", "path": "/categories/3d-animation", "__typename": "ProductCategory"}, {"id": "176", "name": "Maps and GPS", "slug": "maps-and-gps", "path": "/categories/maps-and-gps", "__typename": "ProductCategory"}, {"id": "193", "name": "Apps for kids", "slug": "apps-for-kids", "path": "/categories/apps-for-kids", "__typename": "ProductCategory"}], "tags": ["ios", "education", "augmented reality", "3d & animation", "maps and gps", "apps for kids"], "embeddingSummary": null, "isTopProduct": false, "badges": {"edges": [], "__typename": "Connection"}, "followersCount": 41, "isSubscribed": false, "__typename": "Product", "isNoLongerOnline": false, "founderReviewsCount": 0, "founderShoutouts": []}, "__typename": "ProductEdge"}, {"node": {"id": "557038", "detailedReviewsCount": 4, "postsCount": 1, "latestLaunch": {"id": "421350", "scheduledAt": "2023-11-09T00:40:06-08:00", "__typename": "Post"}, "slug": "threedio", "name": "Threedio", "tagline": "Perfect 3D models for your videos. Consistent & optimized.", "logoUuid": "7b4fce5f-a84a-4a1c-be61-ac92fce5afb8.gif", "reviewsRating": 5.0, "reviewsCount": 4, "categories": [{"id": "66", "name": "3D & Animation", "slug": "3d-animation", "path": "/categories/3d-animation", "__typename": "ProductCategory"}, {"id": "234", "name": "Graphic design tools", "slug": "graphic-design-tools", "path": "/categories/graphic-design-tools", "__typename": "ProductCategory"}, {"id": "235", "name": "Design resources", "slug": "design-resources", "path": "/categories/design-resources", "__typename": "ProductCategory"}], "tags": ["3d modeling", "fbx models", "optimized for 3d apps", "consistent models", "ready-to-use models", "design tools", "marketing", "maker tools", "3d & animation", "graphic design tools", "design resources"], "embeddingSummary": null, "isTopProduct": false, "badges": {"edges": [], "__typename": "Connection"}, "followersCount": 361, "isSubscribed": false, "__typename": "Product", "isNoLongerOnline": false, "founderReviewsCount": 0, "founderShoutouts": []}, "__typename": "ProductEdge"}], "pageInfo": {"hasNextPage": true, "endCursor": "MTIw", "__typename": "PageInfo"}, "totalCount": 266, "__typename": "ProductsConnection"}, "__typename": "ProductCategory"}}}